piglot/__init__.py
piglot/objective.py
piglot/optimiser.py
piglot/parameter.py
piglot/bin/__init__.py
piglot/bin/piglot.py
piglot/bin/piglot_plot.py
piglot/objectives/__init__.py
piglot/objectives/analytical.py
piglot/objectives/design.py
piglot/objectives/fitting.py
piglot/objectives/response_objective.py
piglot/objectives/synthetic.py
piglot/optimisers/__init__.py
piglot/optimisers/aoa.py
piglot/optimisers/direct.py
piglot/optimisers/ga.py
piglot/optimisers/lipo_opt.py
piglot/optimisers/pso.py
piglot/optimisers/query.py
piglot/optimisers/random_search.py
piglot/optimisers/spsa.py
piglot/optimisers/spsa_adam.py
piglot/optimisers/botorch/__init__.py
piglot/optimisers/botorch/bayes.py
piglot/optimisers/botorch/dataset.py
piglot/solver/__init__.py
piglot/solver/input_file_solver.py
piglot/solver/multi_case_solver.py
piglot/solver/script_solver.py
piglot/solver/solver.py
piglot/solver/abaqus/fields.py
piglot/solver/abaqus/reader.py
piglot/solver/abaqus/solver.py
piglot/solver/crate/fields.py
piglot/solver/crate/solver.py
piglot/solver/curve/__init__.py
piglot/solver/curve/solver.py
piglot/solver/links/__init__.py
piglot/solver/links/fields.py
piglot/solver/links/solver.py
piglot/utils/__init__.py
piglot/utils/assorted.py
piglot/utils/reductions.py
piglot/utils/response_transformer.py
piglot/utils/responses.py
piglot/utils/scalarisations.py
piglot/utils/solver_utils.py
piglot/utils/surrogate.py
piglot/utils/yaml_parser.py
piglot/utils/composition/responses.py
piglot-0.5.2.dist-info/licenses/LICENSE
piglot-0.5.2.dist-info/METADATA
piglot-0.5.2.dist-info/WHEEL
piglot-0.5.2.dist-info/entry_points.txt
piglot-0.5.2.dist-info/top_level.txt
piglot-0.5.2.dist-info/RECORD
