Metadata-Version: 2.4
Name: piglot
Version: 0.5.2
Summary: A package for the optimisation of numerical responses
Author: CM2S
Maintainer-email: Rui Coelho <ruicoelhopedro@gmail.com>, Ana Francisca Alves <afalves@fe.up.pt>
Project-URL: Homepage, https://github.com/CM2S/piglot
Project-URL: Documentation, https://piglot.readthedocs.io/en/latest/
Project-URL: Bug Reports, https://github.com/CM2S/piglot/issues
Project-URL: Source, https://github.com/CM2S/piglot/
Keywords: optimisation,parameter identification,constitutive modelling
Classifier: Development Status :: 5 - Production/Stable
Classifier: Intended Audience :: Science/Research
Classifier: Topic :: Scientific/Engineering
Classifier: Topic :: Software Development :: Build Tools
Classifier: License :: OSI Approved :: MIT License
Classifier: Programming Language :: Python :: 3
Classifier: Programming Language :: Python :: 3.9
Classifier: Programming Language :: Python :: 3.10
Classifier: Programming Language :: Python :: 3.11
Classifier: Programming Language :: Python :: 3 :: Only
Requires-Python: >=3.9
License-File: LICENSE
Requires-Dist: numpy
Requires-Dist: tqdm
Requires-Dist: pandas
Requires-Dist: sympy
Requires-Dist: scipy>=1.7
Requires-Dist: torch
Requires-Dist: botorch<=0.13
Requires-Dist: Pillow
Requires-Dist: matplotlib>=3.7.2
Requires-Dist: PyYAML
Requires-Dist: PyQt5
Provides-Extra: lipo
Requires-Dist: lipo; extra == "lipo"
Provides-Extra: genetic
Requires-Dist: geneticalgorithm; extra == "genetic"
Provides-Extra: pso
Requires-Dist: pyswarms; extra == "pso"
Provides-Extra: full
Requires-Dist: lipo; extra == "full"
Requires-Dist: geneticalgorithm; extra == "full"
Requires-Dist: pyswarms; extra == "full"
Provides-Extra: docs
Requires-Dist: sphinx; extra == "docs"
Requires-Dist: myst-parser; extra == "docs"
Requires-Dist: sphinx-rtd-theme; extra == "docs"
Requires-Dist: sphinx-favicon; extra == "docs"
Provides-Extra: test
Requires-Dist: pytest; extra == "test"
Requires-Dist: pytest-cov; extra == "test"
Requires-Dist: flake8; extra == "test"
Requires-Dist: coverage; extra == "test"
Dynamic: license-file
